<annotation><folder>images</folder><filename>augmented_image2_212.jpg</filename><size><width>640</width><height>640</height><depth>3</depth></size><object><name>Zea mays</name><bndbox><xmin>400</xmin><ymin>113</ymin><xmax>495</xmax><ymax>202</ymax></bndbox></object><object><name>Zea mays</name><bndbox><xmin>255</xmin><ymin>93</ymin><xmax>327</xmax><ymax>171</ymax></bndbox></object><object><name>Zea mays</name><bndbox><xmin>307</xmin><ymin>238</ymin><xmax>387</xmax><ymax>326</ymax></bndbox></object><object><name>Zea mays</name><bndbox><xmin>444</xmin><ymin>289</ymin><xmax>552</xmax><ymax>362</ymax></bndbox></object><object><name>Zea mays</name><bndbox><xmin>405</xmin><ymin>401</ymin><xmax>497</xmax><ymax>498</ymax></bndbox></object><object><name>Zea mays</name><bndbox><xmin>202</xmin><ymin>455</ymin><xmax>312</xmax><ymax>533</ymax></bndbox></object><object><name>Zea mays</name><bndbox><xmin>269</xmin><ymin>350</ymin><xmax>341</xmax><ymax>450</ymax></bndbox></object><object><name>Zea mays</name><bndbox><xmin>210</xmin><ymin>219</ymin><xmax>279</xmax><ymax>314</ymax></bndbox></object><object><name>Zea mays</name><bndbox><xmin>104</xmin><ymin>99</ymin><xmax>179</xmax><ymax>197</ymax></bndbox></object><object><name>Zea mays</name><bndbox><xmin>89</xmin><ymin>327</ymin><xmax>186</xmax><ymax>419</ymax></bndbox></object></annotation>